pyliblens/__init__.py
pyliblens/import_info.py
pyliblens/package_info.py
pyliblens/requirement_parser.py
pyliblens-1.0.1.dist-info/WHEEL
pyliblens-1.0.1.dist-info/entry_points.txt
pyliblens-1.0.1.dist-info/METADATA
pyliblens-1.0.1.dist-info/RECORD
