Metadata-Version: 2.3
Name: pyliblens
Version: 1.0.1
Summary: This is a lightweight utility library designed to audit your Python environment
Author: bharathbabu
Author-email: bharathbabu <bharath.r.babu@gmail.com>
Requires-Dist: packaging>=25.0
Requires-Dist: yarg>=0.1.10
Requires-Dist: jinja2>=3.1.6 ; extra == 'report'
Requires-Python: >=3.12
Project-URL: Homepage, https://github.com/babu1993/pyLibLens
Provides-Extra: report
